{
  "homepage": "https://github.com/helpermethod/connect-offset-reset",
  "description": "A commandline tool for resetting Kafka Connect source connector offsets.",
  "version": "0.5.0",
  "license": "Apache-2",
  "url": "https://github.com/helpermethod/connect-offset-reset/releases/download/v0.5.0/connect-offset-reset-0.5.0-windows-x86_64.zip",
  "hash": "sha256:9a738e2650145f325e46e5b50836b9dcb383eeb94ae35942668e53da6d384073",
  "extract_dir": "connect-offset-reset-0.5.0",
  "env_add_path": "bin",
  "checkver": {
    "url": "https://github.com/helpermethod/connect-offset-reset/releases/latest",
    "re": "v([\\d.]+).zip"
  },
  "autoupdate": {
    "url": "https://github.com/helpermethod/connect-offset-reset/releases/download/v$version/connect-offset-reset-$version-windows-x86_64.zip",
    "extract_dir": "connect-offset-reset-$version",
    "hash": {
      "url": "$url.sha256"
    }
  }
}